{
  "data": {
    "canSwim": true,
    "collisionBoxes": [],
    "dropSelf": {
      "canDropSelf": false
    },
    "isOpaqueFullCube": false,
    "isQuad": true,
    "name": {
      "value": "block_water_4"
    },
    "textures": {
      "back": {
        "asset": "plugin/myplugin/block/water_4"
      },
      "down": {
        "asset": "plugin/myplugin/block/water_4"
      },
      "front": {
        "asset": "plugin/myplugin/block/water_4"
      },
      "left": {
        "asset": "plugin/myplugin/block/water_4"
      },
      "right": {
        "asset": "plugin/myplugin/block/water_4"
      },
      "up": {
        "asset": "plugin/myplugin/block/water_4"
      }
    }
  },
  "meta": {
    "EXPORT": {
      "setting.json": "ef6d4d9a0877345dad2b0faf3b76fca7",
      "triggers.bts": ""
    },
    "VERSION": "0.18"
  }
}